odoo/addons/ssi_purchase/README.rst
odoo/addons/ssi_purchase/__init__.py
odoo/addons/ssi_purchase/__manifest__.py
odoo/addons/ssi_purchase/data/approval_template_data.xml
odoo/addons/ssi_purchase/data/ir_sequence_data.xml
odoo/addons/ssi_purchase/data/policy_template_data.xml
odoo/addons/ssi_purchase/data/purchase_order_type.xml
odoo/addons/ssi_purchase/data/sequence_template_data.xml
odoo/addons/ssi_purchase/i18n/ssi_purchase.pot
odoo/addons/ssi_purchase/migrations/14.0.2.0.0/post-migration.py
odoo/addons/ssi_purchase/models/__init__.py
odoo/addons/ssi_purchase/models/purchase_order.py
odoo/addons/ssi_purchase/models/purchase_order_line.py
odoo/addons/ssi_purchase/models/purchase_order_type.py
odoo/addons/ssi_purchase/security/ir.model.access.csv
odoo/addons/ssi_purchase/security/ir_module_category_data.xml
odoo/addons/ssi_purchase/security/ir_rule_data.xml
odoo/addons/ssi_purchase/security/res_group_data.xml
odoo/addons/ssi_purchase/static/description/icon.png
odoo/addons/ssi_purchase/views/product_product_views.xml
odoo/addons/ssi_purchase/views/purchase_order_type_views.xml
odoo/addons/ssi_purchase/views/purchase_order_views.xml
odoo/addons/ssi_purchase/views/res_partner_views.xml
odoo14_addon_ssi_purchase-14.0.4.2.1.dist-info/METADATA
odoo14_addon_ssi_purchase-14.0.4.2.1.dist-info/WHEEL
odoo14_addon_ssi_purchase-14.0.4.2.1.dist-info/top_level.txt
odoo14_addon_ssi_purchase-14.0.4.2.1.dist-info/RECORD
